{"ACTION_NEGATIVE_HIGH": 0.0, "ACTION_NEGATIVE_LOW": -0.1, "ACTION_POSITIVE_HIGH": 0.1, "ACTION_POSITIVE_LOW": 0.0, "CAMERA_INFO_PATH": "real_robots/omnirobot_utils/cam_calib_info.yaml", "CAMERA_POS_COORD_GROUND": [0, 0, 2.9], "CAMERA_ROT_EULER_COORD_GROUND": [0, 180, 0], "CROPPED_SIZE": [480, 480], "DELTA_POS": 0.1, "DIST_TO_TARGET_THRESHOLD": 0.2, "DOWN_KEY": 84, "D_KEY": 100, "ENTER_KEY": 10, "EXIT_KEYS": [113, 27], "HOSTNAME": "localhost", "IMAGE_TOPIC": "/camera/image_raw", "INIT_MAX_X": 0.7, "INIT_MAX_Y": 0.7, "INIT_MIN_X": -0.7, "INIT_MIN_Y": -0.7, "LEFT_KEY": 81, "MAX_DISTANCE": 0, "MAX_STEPS": 250, "MAX_STEPS_CIRCULAR_TASK_SHORT_EPISODES": 75, "MAX_X": 0.85, "MAX_Y": 0.85, "MIN_X": -0.85, "MIN_Y": -0.85, "N_CONTACTS_BEFORE_TERMINATION": 15, "N_DISCRETE_ACTIONS": 4, "OMNIROBOT_L": 0.12, "ORIGIN_SIZE": [640, 480], "RADIUS": 0.6125, "RELATIVE_POS": true, "RENDER_HEIGHT": 224, "RENDER_WIDTH": 224, "REWARD_BUMP_WALL": -1, "REWARD_NOTHING": 0, "REWARD_TARGET_REACH": 1, "RIGHT_KEY": 83, "RL_CONTROL_FREQ": 20.0, "R_KEY": 114, "SECOND_CAM_TOPIC": null, "SERVER_PORT": 7777, "SPACE_KEY": 32, "STEP_DISTANCE": 0.1, "STEP_DISTANCE_TARGET": 0.05, "TARGET_MAX_X": 0.7, "TARGET_MAX_Y": 0.7, "TARGET_MIN_X": -0.7, "TARGET_MIN_Y": -0.7, "UP_KEY": 82, "USING_OMNIROBOT": false, "USING_OMNIROBOT_SIMULATOR": true, "USING_REAL_BAXTER": false, "USING_ROBOBO": false, "U_KEY": 117, "Z_TABLE": 0, "__cached__": "/home/gohu/workspace/robotics-rl-srl/environments/omnirobot_gym/__pycache__/omnirobot_env.cpython-35.pyc", "__doc__": "\nThis program allows to run Omnirobot Gym Environment as a module\n", "__file__": "/home/gohu/workspace/robotics-rl-srl/environments/omnirobot_gym/omnirobot_env.py", "__name__": "environments.omnirobot_gym.omnirobot_env", "__package__": "environments.omnirobot_gym", "action_joints": false, "action_repeat": 1, "chasing_continual_move": false, "circular_continual_move": false, "eight_continual_move": false, "env_rank": 0, "escape_continual_move": true, "is_discrete": true, "learn_states": false, "multi_view": false, "name": "Omnirobot", "random_target": false, "record_data": false, "renders": false, "save_path": "srl_zoo/data/", "shape_reward": false, "short_episodes": false, "simple_continual_target": false, "square_continual_move": false, "srl_model": "raw_pixels", "srl_pipe": null, "state_dim": -1, "state_init_override": null}